<?xml version="1.0" encoding="utf-8"?>
<odoo>
    <!-- object is a presale.order object -->
    <!-- <data noupdate="1"> -->
    <record id="email_template_presale_validated" model="mail.template">
        <field name="name">Presale Order: Send by email</field>
        <field name="subject">object.name</field>
        <field name="email_to">'miad@odoo.com'</field>
        <field name="body_html" type="html">
<div>Your presale order "presale order name here object.name" has been validated.</div>
        </field>
    </record>
    <!-- </data> -->
</odoo>